gpt_pr/__init__.py
gpt_pr/checkversion.py
gpt_pr/config.py
gpt_pr/consolecolor.py
gpt_pr/gh.py
gpt_pr/gitutil.py
gpt_pr/gpt.py
gpt_pr/main.py
gpt_pr/prdata.py
gpt_pr/test_checkversion.py
gpt_pr/test_config.py
gpt_pr/test_gh.py
gpt_pr/test_prdata.py
gpt_pr-0.8.0.dist-info/METADATA
gpt_pr-0.8.0.dist-info/WHEEL
gpt_pr-0.8.0.dist-info/entry_points.txt
gpt_pr-0.8.0.dist-info/RECORD
