Metadata-Version: 2.4
Name: gpt-pr
Version: 0.8.0
Summary: Automate your GitHub workflow with GPT-PR: an OpenAI powered library for streamlined PR generation.
Author: alissonperez
Author-email: 756802+alissonperez@users.noreply.github.com
Requires-Python: >=3.10,<4.0
Classifier: Programming Language :: Python :: 3
Classifier: Programming Language :: Python :: 3.10
Classifier: Programming Language :: Python :: 3.11
Classifier: Programming Language :: Python :: 3.12
Classifier: Programming Language :: Python :: 3.13
Classifier: Programming Language :: Python :: 3.14
Requires-Dist: fire (>=0.7.1,<0.8.0)
Requires-Dist: gitpython (>=3.1.45,<4.0.0)
Requires-Dist: inquirerpy (>=0.3.4,<0.4.0)
Requires-Dist: prompt-toolkit (>=3.0.52,<4.0.0)
Requires-Dist: pydantic-ai (>=1.14.0,<2.0.0)
Requires-Dist: pygithub (>=2.8.1,<3.0.0)
Requires-Dist: requests (>=2.32.5,<3.0.0)
Requires-Dist: tiktoken (>=0.12.0,<0.13.0)
